{
  "lastUpdated": "2025-12-07T04:00:09.909Z",
  "exchangeReserves": {
    "totalBTC": 2345179.894366878,
    "change24h": 0.22150430085037112,
    "change7d": 1.002919293646389,
    "trend": "neutral",
    "exchanges": [
      {
        "name": "Binance",
        "btc": 576693.6030361871,
        "change24h": -0.39879138578033224
      },
      {
        "name": "Coinbase",
        "btc": 421444.07184320164,
        "change24h": -0.8130753601577694
      },
      {
        "name": "Bitfinex",
        "btc": 183415.5477360541,
        "change24h": -0.32590897668729557
      },
      {
        "name": "Kraken",
        "btc": 139345.1589617275,
        "change24h": -0.7259948092196571
      },
      {
        "name": "OKX",
        "btc": 130609.11050112173,
        "change24h": 0.11771373746253433
      }
    ]
  },
  "mvrv": {
    "ratio": 1.93,
    "zone": "fair",
    "marketCap": 1790431536524,
    "realizedCap": 929485415497.4285,
    "signal": "Market in fair value range. Normal accumulation/distribution cycle."
  },
  "whaleFlows": {
    "inflow24h": 0,
    "outflow24h": 0,
    "netFlow24h": 0,
    "flowSignal": "neutral",
    "recentAlerts": 2
  }
}